ruben_calcular_primos/__init__.py
ruben_calcular_primos-1.0.dist-info/LICENSE
ruben_calcular_primos-1.0.dist-info/METADATA
ruben_calcular_primos-1.0.dist-info/WHEEL
ruben_calcular_primos-1.0.dist-info/top_level.txt
ruben_calcular_primos-1.0.dist-info/RECORD
