Metadata-Version: 2.1
Name: ruben-calcular-primos
Version: 1.0
Summary: A tool to calculate prime numbers from 2 to a given number specified by the user.
Home-page: UNKNOWN
Author: Rubén del Mazo
Author-email: ruben.delmazorodriguez@gmail.com
License: GNU GPLv3
Keywords: prime number mathematical operations
Platform: UNKNOWN
Classifier: Development Status :: 4 - Beta
Classifier: Intended Audience :: Developers
Classifier: Topic :: Utilities
Classifier: License :: OSI Approved :: GNU General Public License v3 (GPLv3)
Classifier: Programming Language :: Python :: 3
Classifier: Operating System :: OS Independent
